src/Top.v
module Top(
    input CLK,
    output MDC,
    inout MDIO,
    output [3:0] LED
);

    reg [4:0] mdc_cnt = 0;
    reg mdc_cnt_half = 0;
    reg mdc_cnt_half_flag = 1;
    wire mdclock;
    wire [15:0] mdc_cnt_max;
    reg [15:0] reg_mdc_cnt_max = 30;

    always @(posedge CLK) begin
        mdc_cnt <= mdclock ? 0 : mdc_cnt + 1;
    end

    localparam S_IDLE = 0;
    localparam S_PREAMBLE = 1;
    localparam S_READ = 2;
    localparam S_WRITE = 3;
    localparam S_READ_PREAMBLE = 4;
    localparam S_WRITE_PREAMBLE = 5;
    localparam S_PHY = 6;
    localparam S_REG = 7;
    localparam S_TURN = 8;

    reg [3:0] state = S_IDLE;

    reg [31:0] cnt = 0;
    reg read_flag = 1;

    reg mdio_write = 0;
    reg mdio_out_en = 0;

    assign MDIO = mdio_out_en ? mdio_write : 1'bz;

    reg [3:0] read_preamble = 4'b0110;
    reg [3:0] write_preamble = 4'b0101;

    reg [4:0] reg_phy_address = 5'b00001;
    reg [4:0] reg_register_address = 5'b00000;

    reg [15:0] read = 16'b0;
    reg [15:0] write = 16'b0000111111111010;

    reg [15:0] led_read = 0;

    // STATE MACHINE
    always @(posedge mdclock) begin
        case (state)
            S_IDLE: begin
                state <= S_PREAMBLE;
                mdc_cnt_half <= 0;
            end

            S_PREAMBLE: begin
                if (cnt == 31) begin
                    cnt = 0;
                    if (read_flag == 1'b1)
                        state <= S_READ_PREAMBLE;
                    else
                        state <= S_WRITE_PREAMBLE;
                end else begin
                    state <= S_PREAMBLE;
                    cnt <= cnt + 1;
                end
            end

            S_READ_PREAMBLE: begin
                if (cnt == 3) begin
                    state <= S_PHY;
                    cnt <= 0;
                end else begin
                    state <= S_READ_PREAMBLE;
                    cnt <= cnt + 1;
                end
            end

            S_WRITE_PREAMBLE: begin
                if (cnt == 3) begin
                    state <= S_PHY;
                    cnt <= 0;
                end else begin
                    state <= S_WRITE_PREAMBLE;
                    cnt <= cnt + 1;
                end
            end

            S_PHY: begin
                if (cnt == 4) begin
                    state <= S_REG;
                    cnt <= 0;
                end else begin
                    state <= S_PHY;
                    cnt <= cnt + 1;
                end
            end

            S_REG: begin
                if (cnt == 4) begin
                    state <= S_TURN;
                    cnt <= 0;
                end else begin
                    state <= S_REG;
                    cnt <= cnt + 1;
                end
            end

            S_TURN: begin
                if (cnt == 1) begin
                    if (read_flag == 1)
                        state <= S_READ;
                    else
                        state <= S_WRITE;
                end else begin
                    state <= S_TURN;
                    cnt <= cnt + 1;
                end
            end

            S_READ: begin
                if (cnt == 15) begin
                    state <= S_IDLE;
                    cnt <= 0;
                end else begin
                    state <= S_READ;
                    cnt <= cnt + 1;
                end
            end

            S_WRITE: begin
                if (cnt == 15) begin
                    state <= S_IDLE;
                    cnt <= 0;
                end else begin
                    state <= S_WRITE;
                    cnt <= cnt + 1;
                end
            end
        endcase
    end

    // REG
    always @(posedge CLK) begin
        case (state)
            S_IDLE: begin
                mdio_out_en = 1;
                mdio_write = 0;
                led_read <= read;
            end

            S_PREAMBLE: begin
                mdio_out_en = 1;
                mdio_write = 1;
            end

            S_READ_PREAMBLE: begin
                mdio_out_en = 1;
                mdio_write = read_preamble[cnt];
            end

            S_WRITE_PREAMBLE: begin
                mdio_out_en = 1;
                mdio_write = write_preamble[cnt];
            end

            S_PHY: begin
                mdio_out_en = 1;
                mdio_write = reg_phy_address[4 - cnt];
            end

            S_REG: begin
                mdio_out_en = 1;
                mdio_write = reg_register_address[4 - cnt];
            end

            S_TURN: begin
                mdio_out_en = ~read_flag;
                mdio_write = 0;
            end

            S_READ: begin
                mdio_out_en = 0;
                read[15 - cnt] <= MDIO;
            end

            S_WRITE: begin
                mdio_out_en = 1;
                mdio_write <= write[15 - cnt];
                read_flag <= 1;
            end
        endcase
    end

    assign mdc_cnt_max = reg_mdc_cnt_max;
    assign mdclock = mdc_cnt == mdc_cnt_max;
    assign MDC = mdclock;

    assign LED = ~read[9:6];

endmodule;

src/tb.v
module tb;

    parameter RATE = 1;

    initial begin
        $dumpfile("tb.vcd");
        $dumpvars(3, tb);

        # (270000) $finish;
    end

    reg clk = 0;
    always #(RATE) clk = !clk;

    Top top(
        .CLK(clk)
    );

endmodule

src/tb.vcd
$date
	Thu Jun 15 14:23:44 2023
$end
$version
	Icarus Verilog
$end
$timescale
	1s
$end
$scope module tb $end
$var parameter 32 ! RATE $end
$var reg 1 " clk $end
$scope module top $end
$var wire 1 " CLK $end
$var wire 4 # LED [3:0] $end
$var wire 1 $ MDC $end
$var wire 1 % mdclock $end
$var wire 16 & mdc_cnt_max [15:0] $end
$var wire 1 ' MDIO $end
$var parameter 32 ( S_IDLE $end
$var parameter 32 ) S_PHY $end
$var parameter 32 * S_PREAMBLE $end
$var parameter 32 + S_READ $end
$var parameter 32 , S_READ_PREAMBLE $end
$var parameter 32 - S_REG $end
$var parameter 32 . S_TURN $end
$var parameter 32 / S_WRITE $end
$var parameter 32 0 S_WRITE_PREAMBLE $end
$var reg 32 1 cnt [31:0] $end
$var reg 16 2 led_read [15:0] $end
$var reg 5 3 mdc_cnt [4:0] $end
$var reg 1 4 mdc_cnt_half $end
$var reg 1 5 mdc_cnt_half_flag $end
$var reg 1 6 mdio_out_en $end
$var reg 1 7 mdio_write $end
$var reg 16 8 read [15:0] $end
$var reg 1 9 read_flag $end
$var reg 4 : read_preamble [3:0] $end
$var reg 16 ; reg_mdc_cnt_max [15:0] $end
$var reg 5 < reg_phy_address [4:0] $end
$var reg 5 = reg_register_address [4:0] $end
$var reg 4 > state [3:0] $end
$var reg 16 ? write [15:0] $end
$var reg 4 @ write_preamble [3:0] $end
$upscope $end
$upscope $end
$enddefinitions $end
$comment Show the parameter values. $end
$dumpall
b101 0
b11 /
b1000 .
b111 -
b100 ,
b10 +
b1 *
b110 )
b0 (
b1 !
$end
#0
$dumpvars
b101 @
b111111111010 ?
b0 >
b0 =
b1 <
b11110 ;
b110 :
19
b0 8
07
06
15
04
b0 3
b0 2
b0 1
z'
b11110 &
0%
0$
b1111 #
0"
$end
#1
b1 3
0'
16
1"
#2
0"
#3
b10 3
1"
#4
0"
#5
b11 3
1"
#6
0"
#7
b100 3
1"
#8
0"
#9
b101 3
1"
#10
0"
#11
b110 3
1"
#12
0"
#13
b111 3
1"
#14
0"
#15
b1000 3
1"
#16
0"
#17
b1001 3
1"
#18
0"
#19
b1010 3
1"
#20
0"
#21
b1011 3
1"
#22
0"
#23
b1100 3
1"
#24
0"
#25
b1101 3
1"
#26
0"
#27
b1110 3
1"
#28
0"
#29
b1111 3
1"
#30
0"
#31
b10000 3
1"
#32
0"
#33
b10001 3
1"
#34
0"
#35
b10010 3
1"
#36
0"
#37
b10011 3
1"
#38
0"
#39
b10100 3
1"
#40
0"
#41
b10101 3
1"
#42
0"
#43
b10110 3
1"
#44
0"
#45
b10111 3
1"
#46
0"
#47
b11000 3
1"
#48
0"
#49
b11001 3
1"
#50
0"
#51
b11010 3
1"
#52
0"
#53
b11011 3
1"
#54
0"
#55
b11100 3
1"
#56
0"
#57
b11101 3
1"
#58
0"
#59
b1 >
1$
1%
b11110 3
1"
#60
0"
#61
0$
0%
b0 3
1'
17
1"
#62
0"
#63
b1 3
1"
#64
0"
#65
b10 3
1"
#66
0"
#67
b11 3
1"
#68
0"
#69
b100 3
1"
#70
0"
#71
b101 3
1"
#72
0"
#73
b110 3
1"
#74
0"
#75
b111 3
1"
#76
0"
#77
b1000 3
1"
#78
0"
#79
b1001 3
1"
#80
0"
#81
b1010 3
1"
#82
0"
#83
b1011 3
1"
#84
0"
#85
b1100 3
1"
#86
0"
#87
b1101 3
1"
#88
0"
#89
b1110 3
1"
#90
0"
#91
b1111 3
1"
#92
0"
#93
b10000 3
1"
#94
0"
#95
b10001 3
1"
#96
0"
#97
b10010 3
1"
#98
0"
#99
b10011 3
1"
#100
0"
#101
b10100 3
1"
#102
0"
#103
b10101 3
1"
#104
0"
#105
b10110 3
1"
#106
0"
#107
b10111 3
1"
#108
0"
#109
b11000 3
1"
#110
0"
#111
b11001 3
1"
#112
0"
#113
b11010 3
1"
#114
0"
#115
b11011 3
1"
#116
0"
#117
b11100 3
1"
#118
0"
#119
b11101 3
1"
#120
0"
#121
b1 1
1$
1%
b11110 3
1"
#122
0"
#123
0$
0%
b0 3
1"
#124
0"
#125
b1 3
1"
#126
0"
#127
b10 3
1"
#128
0"
#129
b11 3
1"
#130
0"
#131
b100 3
1"
#132
0"
#133
b101 3
1"
#134
0"
#135
b110 3
1"
#136
0"
#137
b111 3
1"
#138
0"
#139
b1000 3
1"
#140
0"
#141
b1001 3
1"
#142
0"
#143
b1010 3
1"
#144
0"
#145
b1011 3
1"
#146
0"
#147
b1100 3
1"
#148
0"
#149
b1101 3
1"
#150
0"
#151
b1110 3
1"
#152
0"
#153
b1111 3
1"
#154
0"
#155
b10000 3
1"
#156
0"
#157
b10001 3
1"
#158
0"
#159
b10010 3
1"
#160
0"
#161
b10011 3
1"
#162
0"
#163
b10100 3
1"
#164
0"
#165
b10101 3
1"
#166
0"
#167
b10110 3
1"
#168
0"
#169
b10111 3
1"
#170
0"
#171
b11000 3
1"
#172
0"
#173
b11001 3
1"
#174
0"
#175
b11010 3
1"
#176
0"
#177
b11011 3
1"
#178
0"
#179
b11100 3
1"
#180
0"
#181
b11101 3
1"
#182
0"
#183
b10 1
1$
1%
b11110 3
1"
#184
0"
#185
0$
0%
b0 3
1"
#186
0"
#187
b1 3
1"
#188
0"
#189
b10 3
1"
#190
0"
#191
b11 3
1"
#192
0"
#193
b100 3
1"
#194
0"
#195
b101 3
1"
#196
0"
#197
b110 3
1"
#198
0"
#199
b111 3
1"
#200
0"
#201
b1000 3
1"
#202
0"
#203
b1001 3
1"
#204
0"
#205
b1010 3
1"
#206
0"
#207
b1011 3
1"
#208
0"
#209
b1100 3
1"
#210
0"
#211
b1101 3
1"
#212
0"
#213
b1110 3
1"
#214
0"
#215
b1111 3
1"
#216
0"
#217
b10000 3
1"
#218
0"
#219
b10001 3
1"
#220
0"
#221
b10010 3
1"
#222
0"
#223
b10011 3
1"
#224
0"
#225
b10100 3
1"
#226
0"
#227
b10101 3
1"
#228
0"
#229
b10110 3
1"
#230
0"
#231
b10111 3
1"
#232
0"
#233
b11000 3
1"
#234
0"
#235
b11001 3
1"
#236
0"
#237
b11010 3
1"
#238
0"
#239
b11011 3
1"
#240
0"
#241
b11100 3
1"
#242
0"
#243
b11101 3
1"
#244
0"
#245
b11 1
1$
1%
b11110 3
1"
#246
0"
#247
0$
0%
b0 3
1"
#248
0"
#249
b1 3
1"
#250
0"
#251
b10 3
1"
#252
0"
#253
b11 3
1"
#254
0"
#255
b100 3
1"
#256
0"
#257
b101 3
1"
#258
0"
#259
b110 3
1"
#260
0"
#261
b111 3
1"
#262
0"
#263
b1000 3
1"
#264
0"
#265
b1001 3
1"
#266
0"
#267
b1010 3
1"
#268
0"
#269
b1011 3
1"
#270
0"
#271
b1100 3
1"
#272
0"
#273
b1101 3
1"
#274
0"
#275
b1110 3
1"
#276
0"
#277
b1111 3
1"
#278
0"
#279
b10000 3
1"
#280
0"
#281
b10001 3
1"
#282
0"
#283
b10010 3
1"
#284
0"
#285
b10011 3
1"
#286
0"
#287
b10100 3
1"
#288
0"
#289
b10101 3
1"
#290
0"
#291
b10110 3
1"
#292
0"
#293
b10111 3
1"
#294
0"
#295
b11000 3
1"
#296
0"
#297
b11001 3
1"
#298
0"
#299
b11010 3
1"
#300
0"
#301
b11011 3
1"
#302
0"
#303
b11100 3
1"
#304
0"
#305
b11101 3
1"
#306
0"
#307
b100 1
1$
1%
b11110 3
1"
#308
0"
#309
0$
0%
b0 3
1"
#310
0"
#311
b1 3
1"
#312
0"
#313
b10 3
1"
#314
0"
#315
b11 3
1"
#316
0"
#317
b100 3
1"
#318
0"
#319
b101 3
1"
#320
0"
#321
b110 3
1"
#322
0"
#323
b111 3
1"
#324
0"
#325
b1000 3
1"
#326
0"
#327
b1001 3
1"
#328
0"
#329
b1010 3
1"
#330
0"
#331
b1011 3
1"
#332
0"
#333
b1100 3
1"
#334
0"
#335
b1101 3
1"
#336
0"
#337
b1110 3
1"
#338
0"
#339
b1111 3
1"
#340
0"
#341
b10000 3
1"
#342
0"
#343
b10001 3
1"
#344
0"
#345
b10010 3
1"
#346
0"
#347
b10011 3
1"
#348
0"
#349
b10100 3
1"
#350
0"
#351
b10101 3
1"
#352
0"
#353
b10110 3
1"
#354
0"
#355
b10111 3
1"
#356
0"
#357
b11000 3
1"
#358
0"
#359
b11001 3
1"
#360
0"
#361
b11010 3
1"
#362
0"
#363
b11011 3
1"
#364
0"
#365
b11100 3
1"
#366
0"
#367
b11101 3
1"
#368
0"
#369
b101 1
1$
1%
b11110 3
1"
#370
0"
#371
0$
0%
b0 3
1"
#372
0"
#373
b1 3
1"
#374
0"
#375
b10 3
1"
#376
0"
#377
b11 3
1"
#378
0"
#379
b100 3
1"
#380
0"
#381
b101 3
1"
#382
0"
#383
b110 3
1"
#384
0"
#385
b111 3
1"
#386
0"
#387
b1000 3
1"
#388
0"
#389
b1001 3
1"
#390
0"
#391
b1010 3
1"
#392
0"
#393
b1011 3
1"
#394
0"
#395
b1100 3
1"
#396
0"
#397
b1101 3
1"
#398
0"
#399
b1110 3
1"
#400
0"
#401
b1111 3
1"
#402
0"
#403
b10000 3
1"
#404
0"
#405
b10001 3
1"
#406
0"
#407
b10010 3
1"
#408
0"
#409
b10011 3
1"
#410
0"
#411
b10100 3
1"
#412
0"
#413
b10101 3
1"
#414
0"
#415
b10110 3
1"
#416
0"
#417
b10111 3
1"
#418
0"
#419
b11000 3
1"
#420
0"
#421
b11001 3
1"
#422
0"
#423
b11010 3
1"
#424
0"
#425
b11011 3
1"
#426
0"
#427
b11100 3
1"
#428
0"
#429
b11101 3
1"
#430
0"
#431
b110 1
1$
1%
b11110 3
1"
#432
0"
#433
0$
0%
b0 3
1"
#434
0"
#435
b1 3
1"
#436
0"
#437
b10 3
1"
#438
0"
#439
b11 3
1"
#440
0"
#441
b100 3
1"
#442
0"
#443
b101 3
1"
#444
0"
#445
b110 3
1"
#446
0"
#447
b111 3
1"
#448
0"
#449
b1000 3
1"
#450
0"
#451
b1001 3
1"
#452
0"
#453
b1010 3
1"
#454
0"
#455
b1011 3
1"
#456
0"
#457
b1100 3
1"
#458
0"
#459
b1101 3
1"
#460
0"
#461
b1110 3
1"
#462
0"
#463
b1111 3
1"
#464
0"
#465
b10000 3
1"
#466
0"
#467
b10001 3
1"
#468
0"
#469
b10010 3
1"
#470
0"
#471
b10011 3
1"
#472
0"
#473
b10100 3
1"
#474
0"
#475
b10101 3
1"
#476
0"
#477
b10110 3
1"
#478
0"
#479
b10111 3
1"
#480
0"
#481
b11000 3
1"
#482
0"
#483
b11001 3
1"
#484
0"
#485
b11010 3
1"
#486
0"
#487
b11011 3
1"
#488
0"
#489
b11100 3
1"
#490
0"
#491
b11101 3
1"
#492
0"
#493
b111 1
1$
1%
b11110 3
1"
#494
0"
#495
0$
0%
b0 3
1"
#496
0"
#497
b1 3
1"
#498
0"
#499
b10 3
1"
#500
0"
#501
b11 3
1"
#502
0"
#503
b100 3
1"
#504
0"
#505
b101 3
1"
#506
0"
#507
b110 3
1"
#508
0"
#509
b111 3
1"
#510
0"
#511
b1000 3
1"
#512
0"
#513
b1001 3
1"
#514
0"
#515
b1010 3
1"
#516
0"
#517
b1011 3
1"
#518
0"
#519
b1100 3
1"
#520
0"
#521
b1101 3
1"
#522
0"
#523
b1110 3
1"
#524
0"
#525
b1111 3
1"
#526
0"
#527
b10000 3
1"
#528
0"
#529
b10001 3
1"
#530
0"
#531
b10010 3
1"
#532
0"
#533
b10011 3
1"
#534
0"
#535
b10100 3
1"
#536
0"
#537
b10101 3
1"
#538
0"
#539
b10110 3
1"
#540
0"
#541
b10111 3
1"
#542
0"
#543
b11000 3
1"
#544
0"
#545
b11001 3
1"
#546
0"
#547
b11010 3
1"
#548
0"
#549
b11011 3
1"
#550
0"
#551
b11100 3
1"
#552
0"
#553
b11101 3
1"
#554
0"
#555
b1000 1
1$
1%
b11110 3
1"
#556
0"
#557
0$
0%
b0 3
1"
#558
0"
#559
b1 3
1"
#560
0"
#561
b10 3
1"
#562
0"
#563
b11 3
1"
#564
0"
#565
b100 3
1"
#566
0"
#567
b101 3
1"
#568
0"
#569
b110 3
1"
#570
0"
#571
b111 3
1"
#572
0"
#573
b1000 3
1"
#574
0"
#575
b1001 3
1"
#576
0"
#577
b1010 3
1"
#578
0"
#579
b1011 3
1"
#580
0"
#581
b1100 3
1"
#582
0"
#583
b1101 3
1"
#584
0"
#585
b1110 3
1"
#586
0"
#587
b1111 3
1"
#588
0"
#589
b10000 3
1"
#590
0"
#591
b10001 3
1"
#592
0"
#593
b10010 3
1"
#594
0"
#595
b10011 3
1"
#596
0"
#597
b10100 3
1"
#598
0"
#599
b10101 3
1"
#600
0"
#601
b10110 3
1"
#602
0"
#603
b10111 3
1"
#604
0"
#605
b11000 3
1"
#606
0"
#607
b11001 3
1"
#608
0"
#609
b11010 3
1"
#610
0"
#611
b11011 3
1"
#612
0"
#613
b11100 3
1"
#614
0"
#615
b11101 3
1"
#616
0"
#617
b1001 1
1$
1%
b11110 3
1"
#618
0"
#619
0$
0%
b0 3
1"
#620
0"
#621
b1 3
1"
#622
0"
#623
b10 3
1"
#624
0"
#625
b11 3
1"
#626
0"
#627
b100 3
1"
#628
0"
#629
b101 3
1"
#630
0"
#631
b110 3
1"
#632
0"
#633
b111 3
1"
#634
0"
#635
b1000 3
1"
#636
0"
#637
b1001 3
1"
#638
0"
#639
b1010 3
1"
#640
0"
#641
b1011 3
1"
#642
0"
#643
b1100 3
1"
#644
0"
#645
b1101 3
1"
#646
0"
#647
b1110 3
1"
#648
0"
#649
b1111 3
1"
#650
0"
#651
b10000 3
1"
#652
0"
#653
b10001 3
1"
#654
0"
#655
b10010 3
1"
#656
0"
#657
b10011 3
1"
#658
0"
#659
b10100 3
1"
#660
0"
#661
b10101 3
1"
#662
0"
#663
b10110 3
1"
#664
0"
#665
b10111 3
1"
#666
0"
#667
b11000 3
1"
#668
0"
#669
b11001 3
1"
#670
0"
#671
b11010 3
1"
#672
0"
#673
b11011 3
1"
#674
0"
#675
b11100 3
1"
#676
0"
#677
b11101 3
1"
#678
0"
#679
b1010 1
1$
1%
b11110 3
1"
#680
0"
#681
0$
0%
b0 3
1"
#682
0"
#683
b1 3
1"
#684
0"
#685
b10 3
1"
#686
0"
#687
b11 3
1"
#688
0"
#689
b100 3
1"
#690
0"
#691
b101 3
1"
#692
0"
#693
b110 3
1"
#694
0"
#695
b111 3
1"
#696
0"
#697
b1000 3
1"
#698
0"
#699
b1001 3
1"
#700
0"
#701
b1010 3
1"
#702
0"
#703
b1011 3
1"
#704
0"
#705
b1100 3
1"
#706
0"
#707
b1101 3
1"
#708
0"
#709
b1110 3
1"
#710
0"
#711
b1111 3
1"
#712
0"
#713
b10000 3
1"
#714
0"
#715
b10001 3
1"
#716
0"
#717
b10010 3
1"
#718
0"
#719
b10011 3
1"
#720
0"
#721
b10100 3
1"
#722
0"
#723
b10101 3
1"
#724
0"
#725
b10110 3
1"
#726
0"
#727
b10111 3
1"
#728
0"
#729
b11000 3
1"
#730
0"
#731
b11001 3
1"
#732
0"
#733
b11010 3
1"
#734
0"
#735
b11011 3
1"
#736
0"
#737
b11100 3
1"
#738
0"
#739
b11101 3
1"
#740
0"
#741
b1011 1
1$
1%
b11110 3
1"
#742
0"
#743
0$
0%
b0 3
1"
#744
0"
#745
b1 3
1"
#746
0"
#747
b10 3
1"
#748
0"
#749
b11 3
1"
#750
0"
#751
b100 3
1"
#752
0"
#753
b101 3
1"
#754
0"
#755
b110 3
1"
#756
0"
#757
b111 3
1"
#758
0"
#759
b1000 3
1"
#760
0"
#761
b1001 3
1"
#762
0"
#763
b1010 3
1"
#764
0"
#765
b1011 3
1"
#766
0"
#767
b1100 3
1"
#768
0"
#769
b1101 3
1"
#770
0"
#771
b1110 3
1"
#772
0"
#773
b1111 3
1"
#774
0"
#775
b10000 3
1"
#776
0"
#777
b10001 3
1"
#778
0"
#779
b10010 3
1"
#780
0"
#781
b10011 3
1"
#782
0"
#783
b10100 3
1"
#784
0"
#785
b10101 3
1"
#786
0"
#787
b10110 3
1"
#788
0"
#789
b10111 3
1"
#790
0"
#791
b11000 3
1"
#792
0"
#793
b11001 3
1"
#794
0"
#795
b11010 3
1"
#796
0"
#797
b11011 3
1"
#798
0"
#799
b11100 3
1"
#800
0"
#801
b11101 3
1"
#802
0"
#803
b1100 1
1$
1%
b11110 3
1"
#804
0"
#805
0$
0%
b0 3
1"
#806
0"
#807
b1 3
1"
#808
0"
#809
b10 3
1"
#810
0"
#811
b11 3
1"
#812
0"
#813
b100 3
1"
#814
0"
#815
b101 3
1"
#816
0"
#817
b110 3
1"
#818
0"
#819
b111 3
1"
#820
0"
#821
b1000 3
1"
#822
0"
#823
b1001 3
1"
#824
0"
#825
b1010 3
1"
#826
0"
#827
b1011 3
1"
#828
0"
#829
b1100 3
1"
#830
0"
#831
b1101 3
1"
#832
0"
#833
b1110 3
1"
#834
0"
#835
b1111 3
1"
#836
0"
#837
b10000 3
1"
#838
0"
#839
b10001 3
1"
#840
0"
#841
b10010 3
1"
#842
0"
#843
b10011 3
1"
#844
0"
#845
b10100 3
1"
#846
0"
#847
b10101 3
1"
#848
0"
#849
b10110 3
1"
#850
0"
#851
b10111 3
1"
#852
0"
#853
b11000 3
1"
#854
0"
#855
b11001 3
1"
#856
0"
#857
b11010 3
1"
#858
0"
#859
b11011 3
1"
#860
0"
#861
b11100 3
1"
#862
0"
#863
b11101 3
1"
#864
0"
#865
b1101 1
1$
1%
b11110 3
1"
#866
0"
#867
0$
0%
b0 3
1"
#868
0"
#869
b1 3
1"
#870
0"
#871
b10 3
1"
#872
0"
#873
b11 3
1"
#874
0"
#875
b100 3
1"
#876
0"
#877
b101 3
1"
#878
0"
#879
b110 3
1"
#880
0"
#881
b111 3
1"
#882
0"
#883
b1000 3
1"
#884
0"
#885
b1001 3
1"
#886
0"
#887
b1010 3
1"
#888
0"
#889
b1011 3
1"
#890
0"
#891
b1100 3
1"
#892
0"
#893
b1101 3
1"
#894
0"
#895
b1110 3
1"
#896
0"
#897
b1111 3
1"
#898
0"
#899
b10000 3
1"
#900
0"
#901
b10001 3
1"
#902
0"
#903
b10010 3
1"
#904
0"
#905
b10011 3
1"
#906
0"
#907
b10100 3
1"
#908
0"
#909
b10101 3
1"
#910
0"
#911
b10110 3
1"
#912
0"
#913
b10111 3
1"
#914
0"
#915
b11000 3
1"
#916
0"
#917
b11001 3
1"
#918
0"
#919
b11010 3
1"
#920
0"
#921
b11011 3
1"
#922
0"
#923
b11100 3
1"
#924
0"
#925
b11101 3
1"
#926
0"
#927
b1110 1
1$
1%
b11110 3
1"
#928
0"
#929
0$
0%
b0 3
1"
#930
0"
#931
b1 3
1"
#932
0"
#933
b10 3
1"
#934
0"
#935
b11 3
1"
#936
0"
#937
b100 3
1"
#938
0"
#939
b101 3
1"
#940
0"
#941
b110 3
1"
#942
0"
#943
b111 3
1"
#944
0"
#945
b1000 3
1"
#946
0"
#947
b1001 3
1"
#948
0"
#949
b1010 3
1"
#950
0"
#951
b1011 3
1"
#952
0"
#953
b1100 3
1"
#954
0"
#955
b1101 3
1"
#956
0"
#957
b1110 3
1"
#958
0"
#959
b1111 3
1"
#960
0"
#961
b10000 3
1"
#962
0"
#963
b10001 3
1"
#964
0"
#965
b10010 3
1"
#966
0"
#967
b10011 3
1"
#968
0"
#969
b10100 3
1"
#970
0"
#971
b10101 3
1"
#972
0"
#973
b10110 3
1"
#974
0"
#975
b10111 3
1"
#976
0"
#977
b11000 3
1"
#978
0"
#979
b11001 3
1"
#980
0"
#981
b11010 3
1"
#982
0"
#983
b11011 3
1"
#984
0"
#985
b11100 3
1"
#986
0"
#987
b11101 3
1"
#988
0"
#989
b1111 1
1$
1%
b11110 3
1"
#990
0"
#991
0$
0%
b0 3
1"
#992
0"
#993
b1 3
1"
#994
0"
#995
b10 3
1"
#996
0"
#997
b11 3
1"
#998
0"
#999
b100 3
1"
#1000
0"
#1001
b101 3
1"
#1002
0"
#1003
b110 3
1"
#1004
0"
#1005
b111 3
1"
#1006
0"
#1007
b1000 3
1"
#1008
0"
#1009
b1001 3
1"
#1010
0"
#1011
b1010 3
1"
#1012
0"
#1013
b1011 3
1"
#1014
0"
#1015
b1100 3
1"
#1016
0"
#1017
b1101 3
1"
#1018
0"
#1019
b1110 3
1"
#1020
0"
#1021
b1111 3
1"
#1022
0"
#1023
b10000 3
1"
#1024
0"
#1025
b10001 3
1"
#1026
0"
#1027
b10010 3
1"
#1028
0"
#1029
b10011 3
1"
#1030
0"
#1031
b10100 3
1"
#1032
0"
#1033
b10101 3
1"
#1034
0"
#1035
b10110 3
1"
#1036
0"
#1037
b10111 3
1"
#1038
0"
#1039
b11000 3
1"
#1040
0"
#1041
b11001 3
1"
#1042
0"
#1043
b11010 3
1"
#1044
0"
#1045
b11011 3
1"
#1046
0"
#1047
b11100 3
1"
#1048
0"
#1049
b11101 3
1"
#1050
0"
#1051
b10000 1
1$
1%
b11110 3
1"
#1052
0"
#1053
0$
0%
b0 3
1"
#1054
0"
#1055
b1 3
1"
#1056
0"
#1057
b10 3
1"
#1058
0"
#1059
b11 3
1"
#1060
0"
#1061
b100 3
1"
#1062
0"
#1063
b101 3
1"
#1064
0"
#1065
b110 3
1"
#1066
0"
#1067
b111 3
1"
#1068
0"
#1069
b1000 3
1"
#1070
0"
#1071
b1001 3
1"
#1072
0"
#1073
b1010 3
1"
#1074
0"
#1075
b1011 3
1"
#1076
0"
#1077
b1100 3
1"
#1078
0"
#1079
b1101 3
1"
#1080
0"
#1081
b1110 3
1"
#1082
0"
#1083
b1111 3
1"
#1084
0"
#1085
b10000 3
1"
#1086
0"
#1087
b10001 3
1"
#1088
0"
#1089
b10010 3
1"
#1090
0"
#1091
b10011 3
1"
#1092
0"
#1093
b10100 3
1"
#1094
0"
#1095
b10101 3
1"
#1096
0"
#1097
b10110 3
1"
#1098
0"
#1099
b10111 3
1"
#1100
0"
#1101
b11000 3
1"
#1102
0"
#1103
b11001 3
1"
#1104
0"
#1105
b11010 3
1"
#1106
0"
#1107
b11011 3
1"
#1108
0"
#1109
b11100 3
1"
#1110
0"
#1111
b11101 3
1"
#1112
0"
#1113
b10001 1
1$
1%
b11110 3
1"
#1114
0"
#1115
0$
0%
b0 3
1"
#1116
0"
#1117
b1 3
1"
#1118
0"
#1119
b10 3
1"
#1120
0"
#1121
b11 3
1"
#1122
0"
#1123
b100 3
1"
#1124
0"
#1125
b101 3
1"
#1126
0"
#1127
b110 3
1"
#1128
0"
#1129
b111 3
1"
#1130
0"
#1131
b1000 3
1"
#1132
0"
#1133
b1001 3
1"
#1134
0"
#1135
b1010 3
1"
#1136
0"
#1137
b1011 3
1"
#1138
0"
#1139
b1100 3
1"
#1140
0"
#1141
b1101 3
1"
#1142
0"
#1143
b1110 3
1"
#1144
0"
#1145
b1111 3
1"
#1146
0"
#1147
b10000 3
1"
#1148
0"
#1149
b10001 3
1"
#1150
0"
#1151
b10010 3
1"
#1152
0"
#1153
b10011 3
1"
#1154
0"
#1155
b10100 3
1"
#1156
0"
#1157
b10101 3
1"
#1158
0"
#1159
b10110 3
1"
#1160
0"
#1161
b10111 3
1"
#1162
0"
#1163
b11000 3
1"
#1164
0"
#1165
b11001 3
1"
#1166
0"
#1167
b11010 3
1"
#1168
0"
#1169
b11011 3
1"
#1170
0"
#1171
b11100 3
1"
#1172
0"
#1173
b11101 3
1"
#1174
0"
#1175
b10010 1
1$
1%
b11110 3
1"
#1176
0"
#1177
0$
0%
b0 3
1"
#1178
0"
#1179
b1 3
1"
#1180
0"
#1181
b10 3
1"
#1182
0"
#1183
b11 3
1"
#1184
0"
#1185
b100 3
1"
#1186
0"
#1187
b101 3
1"
#1188
0"
#1189
b110 3
1"
#1190
0"
#1191
b111 3
1"
#1192
0"
#1193
b1000 3
1"
#1194
0"
#1195
b1001 3
1"
#1196
0"
#1197
b1010 3
1"
#1198
0"
#1199
b1011 3
1"
#1200
0"
#1201
b1100 3
1"
#1202
0"
#1203
b1101 3
1"
#1204
0"
#1205
b1110 3
1"
#1206
0"
#1207
b1111 3
1"
#1208
0"
#1209
b10000 3
1"
#1210
0"
#1211
b10001 3
1"
#1212
0"
#1213
b10010 3
1"
#1214
0"
#1215
b10011 3
1"
#1216
0"
#1217
b10100 3
1"
#1218
0"
#1219
b10101 3
1"
#1220
0"
#1221
b10110 3
1"
#1222
0"
#1223
b10111 3
1"
#1224
0"
#1225
b11000 3
1"
#1226
0"
#1227
b11001 3
1"
#1228
0"
#1229
b11010 3
1"
#1230
0"
#1231
b11011 3
1"
#1232
0"
#1233
b11100 3
1"
#1234
0"
#1235
b11101 3
1"
#1236
0"
#1237
b10011 1
1$
1%
b11110 3
1"
#1238
0"
#1239
0$
0%
b0 3
1"
#1240
0"
#1241
b1 3
1"
#1242
0"
#1243
b10 3
1"
#1244
0"
#1245
b11 3
1"
#1246
0"
#1247
b100 3
1"
#1248
0"
#1249
b101 3
1"
#1250
0"
#1251
b110 3
1"
#1252
0"
#1253
b111 3
1"
#1254
0"
#1255
b1000 3
1"
#1256
0"
#1257
b1001 3
1"
#1258
0"
#1259
b1010 3
1"
#1260
0"
#1261
b1011 3
1"
#1262
0"
#1263
b1100 3
1"
#1264
0"
#1265
b1101 3
1"
#1266
0"
#1267
b1110 3
1"
#1268
0"
#1269
b1111 3
1"
#1270
0"
#1271
b10000 3
1"
#1272
0"
#1273
b10001 3
1"
