src/Top.v
module Top(
    input CLK,
    output MDC,
    inout MDIO,
    output [3:0] LED
);

    reg [4:0] mdc_cnt = 0;
    wire mdclock;

    always @(posedge CLK) begin
        mdc_cnt <= mdclock ? 0 : mdc_cnt + 1;
    end

    localparam S_IDLE = 0;
    localparam S_PREAMBLE = 1;
    localparam S_READ = 2;
    localparam S_WRITE = 3;
    localparam S_READ_PREAMBLE = 4;
    localparam S_WRITE_PREAMBLE = 5;
    localparam S_PHY = 6;
    localparam S_REG = 7;
    localparam S_TURN = 8;

    reg [3:0] state = S_IDLE;

    reg [31:0] cnt = 0;
    reg read_flag = 1;

    reg mdio_write = 0;
    reg mdio_out_en = 0;

    assign MDIO = mdio_out_en ? mdio_write : 1'bz;

    reg [3:0] read_preamble = 4'b0110;
    reg [3:0] write_preamble = 4'b0101;

    reg [4:0] reg_phy_address = 5'b00001;
    reg [4:0] reg_register_address = 5'b00000;

    reg [15:0] read = 0;
    reg [15:0] write = 16'b0000111111111010;

    reg [15:0] led_read = 0;

    // STATE MACHINE
    always @(posedge mdclock) begin
        case (state)
            S_IDLE: begin
                state <= S_PREAMBLE;
            end

            S_PREAMBLE: begin
                if (cnt == 31) begin
                    cnt = 0;
                    if (read_flag == 1'b1)
                        state <= S_READ_PREAMBLE;
                    else
                        state <= S_WRITE_PREAMBLE;
                end else begin
                    state <= S_PREAMBLE;
                    cnt <= cnt + 1;
                end
            end

            S_READ_PREAMBLE: begin
                if (cnt == 3) begin
                    state <= S_PHY;
                    cnt <= 0;
                end else begin
                    state <= S_READ_PREAMBLE;
                    cnt <= cnt + 1;
                end
            end

            S_WRITE_PREAMBLE: begin
                if (cnt == 3) begin
                    state <= S_PHY;
                    cnt <= 0;
                end else begin
                    state <= S_WRITE_PREAMBLE;
                    cnt <= cnt + 1;
                end
            end

            S_PHY: begin
                if (cnt == 4) begin
                    state <= S_REG;
                    cnt <= 0;
                end else begin
                    state <= S_PHY;
                    cnt <= cnt + 1;
                end
            end

            S_REG: begin
                if (cnt == 4) begin
                    state <= S_TURN;
                    cnt <= 0;
                end else begin
                    state <= S_REG;
                    cnt <= cnt + 1;
                end
            end

            S_TURN: begin
                if (cnt == 1) begin
                    cnt <= 0;
                    if (read_flag == 1)
                        state <= S_READ;
                    else
                        state <= S_WRITE;
                end else begin
                    state <= S_TURN;
                    cnt <= cnt + 1;
                end
            end

            S_READ: begin
                if (cnt == 15) begin
                    state <= S_IDLE;
                    cnt <= 0;
                end else begin
                    state <= S_READ;
                    cnt <= cnt + 1;
                end
            end

            S_WRITE: begin
                if (cnt == 15) begin
                    state <= S_IDLE;
                    cnt <= 0;
                end else begin
                    state <= S_WRITE;
                    cnt <= cnt + 1;
                end
            end
        endcase
    end

    // REG
    always @(posedge CLK) begin
        case (state)
            S_IDLE: begin
                mdio_out_en = 1;
                mdio_write = 0;
                led_read <= read;
            end

            S_PREAMBLE: begin
                mdio_out_en = 1;
                mdio_write = 1;
            end

            S_READ_PREAMBLE: begin
                mdio_out_en = 1;
                mdio_write = read_preamble[cnt];
            end

            S_WRITE_PREAMBLE: begin
                mdio_out_en = 1;
                mdio_write = write_preamble[cnt];
            end

            S_PHY: begin
                mdio_out_en = 1;
                mdio_write = reg_phy_address[4 - cnt];
            end

            S_REG: begin
                mdio_out_en = 1;
                mdio_write = reg_register_address[4 - cnt];
            end

            S_TURN: begin
                mdio_out_en = ~read_flag;
                mdio_write = 0;
            end

            S_READ: begin
                mdio_out_en = 0;
                read[15 - cnt] <= MDIO;
            end

            S_WRITE: begin
                mdio_out_en = 1;
                mdio_write <= write[15 - cnt];
                read_flag <= 1;
            end
        endcase
    end

    assign mdclock = mdc_cnt == 27;
    assign MDC = mdclock;

    assign LED = ~read[9:6];

endmodule;

src/tb.v
module tb;

    parameter RATE = 1;

    initial begin
        $dumpfile("tb.vcd");
        $dumpvars(3, tb);

        # (270000) $finish;
    end

    reg clk = 0;
    always #(RATE) clk = !clk;

    Top top(
        .CLK(clk)
    );

endmodule

src/tb.vcd
$date
	Thu Jun 15 15:27:09 2023
$end
$version
	Icarus Verilog
$end
$timescale
	1s
$end
$scope module tb $end
$var parameter 32 ! RATE $end
$var reg 1 " clk $end
$scope module top $end
$var wire 1 " CLK $end
$var wire 4 # LED [3:0] $end
$var wire 1 $ MDC $end
$var wire 1 % mdclock $end
$var wire 1 & MDIO $end
$var parameter 32 ' S_IDLE $end
$var parameter 32 ( S_PHY $end
$var parameter 32 ) S_PREAMBLE $end
$var parameter 32 * S_READ $end
$var parameter 32 + S_READ_PREAMBLE $end
$var parameter 32 , S_REG $end
$var parameter 32 - S_TURN $end
$var parameter 32 . S_WRITE $end
$var parameter 32 / S_WRITE_PREAMBLE $end
$var reg 32 0 cnt [31:0] $end
$var reg 16 1 led_read [15:0] $end
$var reg 5 2 mdc_cnt [4:0] $end
$var reg 1 3 mdio_out_en $end
$var reg 1 4 mdio_write $end
$var reg 16 5 read [15:0] $end
$var reg 1 6 read_flag $end
$var reg 4 7 read_preamble [3:0] $end
$var reg 5 8 reg_phy_address [4:0] $end
$var reg 5 9 reg_register_address [4:0] $end
$var reg 4 : state [3:0] $end
$var reg 16 ; write [15:0] $end
$var reg 4 < write_preamble [3:0] $end
$upscope $end
$upscope $end
$enddefinitions $end
$comment Show the parameter values. $end
$dumpall
b101 /
b11 .
b1000 -
b111 ,
b100 +
b10 *
b1 )
b110 (
b0 '
b1 !
$end
#0
$dumpvars
b101 <
b111111111010 ;
b0 :
b0 9
b1 8
b110 7
16
b0 5
04
03
b0 2
b0 1
b0 0
z&
0%
0$
b1111 #
0"
$end
#1
b1 2
0&
13
1"
#2
0"
#3
b10 2
1"
#4
0"
#5
b11 2
1"
#6
0"
#7
b100 2
1"
#8
0"
#9
b101 2
1"
#10
0"
#11
b110 2
1"
#12
0"
#13
b111 2
1"
#14
0"
#15
b1000 2
1"
#16
0"
#17
b1001 2
1"
#18
0"
#19
b1010 2
1"
#20
0"
#21
b1011 2
1"
#22
0"
#23
b1100 2
1"
#24
0"
#25
b1101 2
1"
#26
0"
#27
b1110 2
1"
#28
0"
#29
b1111 2
1"
#30
0"
#31
b10000 2
1"
#32
0"
#33
b10001 2
1"
#34
0"
#35
b10010 2
1"
#36
0"
#37
b10011 2
1"
#38
0"
#39
b10100 2
1"
#40
0"
#41
b10101 2
1"
#42
0"
#43
b10110 2
1"
#44
0"
#45
b10111 2
1"
#46
0"
#47
b11000 2
1"
#48
0"
#49
b11001 2
1"
#50
0"
#51
b11010 2
1"
#52
0"
#53
b1 :
1$
1%
b11011 2
1"
#54
0"
#55
0$
0%
b0 2
1&
14
1"
#56
0"
#57
b1 2
1"
#58
0"
#59
b10 2
1"
#60
0"
#61
b11 2
1"
#62
0"
#63
b100 2
1"
#64
0"
#65
b101 2
1"
#66
0"
#67
b110 2
1"
#68
0"
#69
b111 2
1"
#70
0"
#71
b1000 2
1"
#72
0"
#73
b1001 2
1"
#74
0"
#75
b1010 2
1"
#76
0"
#77
b1011 2
1"
#78
0"
#79
b1100 2
1"
#80
0"
#81
b1101 2
1"
#82
0"
#83
b1110 2
1"
#84
0"
#85
b1111 2
1"
#86
0"
#87
b10000 2
1"
#88
0"
#89
b10001 2
1"
#90
0"
#91
b10010 2
1"
#92
0"
#93
b10011 2
1"
#94
0"
#95
b10100 2
1"
#96
0"
#97
b10101 2
1"
#98
0"
#99
b10110 2
1"
#100
0"
#101
b10111 2
1"
#102
0"
#103
b11000 2
1"
#104
0"
#105
b11001 2
1"
#106
0"
#107
b11010 2
1"
#108
0"
#109
b1 0
1$
1%
b11011 2
1"
#110
0"
#111
0$
0%
b0 2
1"
#112
0"
#113
b1 2
1"
#114
0"
#115
b10 2
1"
#116
0"
#117
b11 2
1"
#118
0"
#119
b100 2
1"
#120
0"
#121
b101 2
1"
#122
0"
#123
b110 2
1"
#124
0"
#125
b111 2
1"
#126
0"
#127
b1000 2
1"
#128
0"
#129
b1001 2
1"
#130
0"
#131
b1010 2
1"
#132
0"
#133
b1011 2
1"
#134
0"
#135
b1100 2
1"
#136
0"
#137
b1101 2
1"
#138
0"
#139
b1110 2
1"
#140
0"
#141
b1111 2
1"
#142
0"
#143
b10000 2
1"
#144
0"
#145
b10001 2
1"
#146
0"
#147
b10010 2
1"
#148
0"
#149
b10011 2
1"
#150
0"
#151
b10100 2
1"
#152
0"
#153
b10101 2
1"
#154
0"
#155
b10110 2
1"
#156
0"
#157
b10111 2
1"
#158
0"
#159
b11000 2
1"
#160
0"
#161
b11001 2
1"
#162
0"
#163
b11010 2
1"
#164
0"
#165
b10 0
1$
1%
b11011 2
1"
#166
0"
#167
0$
0%
b0 2
1"
#168
0"
#169
b1 2
1"
#170
0"
#171
b10 2
1"
#172
0"
#173
b11 2
1"
#174
0"
#175
b100 2
1"
#176
0"
#177
b101 2
1"
#178
0"
#179
b110 2
1"
#180
0"
#181
b111 2
1"
#182
0"
#183
b1000 2
1"
#184
0"
#185
b1001 2
1"
#186
0"
#187
b1010 2
1"
#188
0"
#189
b1011 2
1"
#190
0"
#191
b1100 2
1"
#192
0"
#193
b1101 2
1"
#194
0"
#195
b1110 2
1"
#196
0"
#197
b1111 2
1"
#198
0"
#199
b10000 2
1"
#200
0"
#201
b10001 2
1"
#202
0"
#203
b10010 2
1"
#204
0"
#205
b10011 2
1"
#206
0"
#207
b10100 2
1"
#208
0"
#209
b10101 2
1"
#210
0"
#211
b10110 2
1"
#212
0"
#213
b10111 2
1"
#214
0"
#215
b11000 2
1"
#216
0"
#217
b11001 2
1"
#218
0"
#219
b11010 2
1"
#220
0"
#221
b11 0
1$
1%
b11011 2
1"
#222
0"
#223
0$
0%
b0 2
1"
#224
0"
#225
b1 2
1"
#226
0"
#227
b10 2
1"
#228
0"
#229
b11 2
1"
#230
0"
#231
b100 2
1"
#232
0"
#233
b101 2
1"
#234
0"
#235
b110 2
1"
#236
0"
#237
b111 2
1"
#238
0"
#239
b1000 2
1"
#240
0"
#241
b1001 2
1"
#242
0"
#243
b1010 2
1"
#244
0"
#245
b1011 2
1"
#246
0"
#247
b1100 2
1"
#248
0"
#249
b1101 2
1"
#250
0"
#251
b1110 2
1"
#252
0"
#253
b1111 2
1"
#254
0"
#255
b10000 2
1"
#256
0"
#257
b10001 2
1"
#258
0"
#259
b10010 2
1"
#260
0"
#261
b10011 2
1"
#262
0"
#263
b10100 2
1"
#264
0"
#265
b10101 2
1"
#266
0"
#267
b10110 2
1"
#268
0"
#269
b10111 2
1"
#270
0"
#271
b11000 2
1"
#272
0"
#273
b11001 2
1"
#274
0"
#275
b11010 2
1"
#276
0"
#277
b100 0
1$
1%
b11011 2
1"
#278
0"
#279
0$
0%
b0 2
1"
#280
0"
#281
b1 2
1"
#282
0"
#283
b10 2
1"
#284
0"
#285
b11 2
1"
#286
0"
#287
b100 2
1"
#288
0"
#289
b101 2
1"
#290
0"
#291
b110 2
1"
#292
0"
#293
b111 2
1"
#294
0"
#295
b1000 2
1"
#296
0"
#297
b1001 2
1"
#298
0"
#299
b1010 2
1"
#300
0"
#301
b1011 2
1"
#302
0"
#303
b1100 2
1"
#304
0"
#305
b1101 2
1"
#306
0"
#307
b1110 2
1"
#308
0"
#309
b1111 2
1"
#310
0"
#311
b10000 2
1"
#312
0"
#313
b10001 2
1"
#314
0"
#315
b10010 2
1"
#316
0"
#317
b10011 2
1"
#318
0"
#319
b10100 2
1"
#320
0"
#321
b10101 2
1"
#322
0"
#323
b10110 2
1"
#324
0"
#325
b10111 2
1"
#326
0"
#327
b11000 2
1"
#328
0"
#329
b11001 2
1"
#330
0"
#331
b11010 2
1"
#332
0"
#333
b101 0
1$
1%
b11011 2
1"
#334
0"
#335
0$
0%
b0 2
1"
#336
0"
#337
b1 2
1"
#338
0"
#339
b10 2
1"
#340
0"
#341
b11 2
1"
#342
0"
#343
b100 2
1"
#344
0"
#345
b101 2
1"
#346
0"
#347
b110 2
1"
#348
0"
#349
b111 2
1"
#350
0"
#351
b1000 2
1"
#352
0"
#353
b1001 2
1"
#354
0"
#355
b1010 2
1"
#356
0"
#357
b1011 2
1"
#358
0"
#359
b1100 2
1"
#360
0"
#361
b1101 2
1"
#362
0"
#363
b1110 2
1"
#364
0"
#365
b1111 2
1"
#366
0"
#367
b10000 2
1"
#368
0"
#369
b10001 2
1"
#370
0"
#371
b10010 2
1"
#372
0"
#373
b10011 2
1"
#374
0"
#375
b10100 2
1"
#376
0"
#377
b10101 2
1"
#378
0"
#379
b10110 2
1"
#380
0"
#381
b10111 2
1"
#382
0"
#383
b11000 2
1"
#384
0"
#385
b11001 2
1"
#386
0"
#387
b11010 2
1"
#388
0"
#389
b110 0
1$
1%
b11011 2
1"
#390
0"
#391
0$
0%
b0 2
1"
#392
0"
#393
b1 2
1"
#394
0"
#395
b10 2
1"
#396
0"
#397
b11 2
1"
#398
0"
#399
b100 2
1"
#400
0"
#401
b101 2
1"
#402
0"
#403
b110 2
1"
#404
0"
#405
b111 2
1"
#406
0"
#407
b1000 2
1"
#408
0"
#409
b1001 2
1"
#410
0"
#411
b1010 2
1"
#412
0"
#413
b1011 2
1"
#414
0"
#415
b1100 2
1"
#416
0"
#417
b1101 2
1"
#418
0"
#419
b1110 2
1"
#420
0"
#421
b1111 2
1"
#422
0"
#423
b10000 2
1"
#424
0"
#425
b10001 2
1"
#426
0"
#427
b10010 2
1"
#428
0"
#429
b10011 2
1"
#430
0"
#431
b10100 2
1"
#432
0"
#433
b10101 2
1"
#434
0"
#435
b10110 2
1"
#436
0"
#437
b10111 2
1"
#438
0"
#439
b11000 2
1"
#440
0"
#441
b11001 2
1"
#442
0"
#443
b11010 2
1"
#444
0"
#445
b111 0
1$
1%
b11011 2
1"
#446
0"
#447
0$
0%
b0 2
1"
#448
0"
#449
b1 2
1"
#450
0"
#451
b10 2
1"
#452
0"
#453
b11 2
1"
#454
0"
#455
b100 2
1"
#456
0"
#457
b101 2
1"
#458
0"
#459
b110 2
1"
#460
0"
#461
b111 2
1"
#462
0"
#463
b1000 2
1"
#464
0"
#465
b1001 2
1"
#466
0"
#467
b1010 2
1"
#468
0"
#469
b1011 2
1"
#470
0"
#471
b1100 2
1"
#472
0"
#473
b1101 2
1"
#474
0"
#475
b1110 2
1"
#476
0"
#477
b1111 2
1"
#478
0"
#479
b10000 2
1"
#480
0"
#481
b10001 2
1"
#482
0"
#483
b10010 2
1"
#484
0"
#485
b10011 2
1"
#486
0"
#487
b10100 2
1"
#488
0"
#489
b10101 2
1"
#490
0"
#491
b10110 2
1"
#492
0"
#493
b10111 2
1"
#494
0"
#495
b11000 2
1"
#496
0"
#497
b11001 2
1"
#498
0"
#499
b11010 2
1"
#500
0"
#501
b1000 0
1$
1%
b11011 2
1"
#502
0"
#503
0$
0%
b0 2
1"
#504
0"
#505
b1 2
1"
#506
0"
#507
b10 2
1"
#508
0"
#509
b11 2
1"
#510
0"
#511
b100 2
1"
#512
0"
#513
b101 2
1"
#514
0"
#515
b110 2
1"
#516
0"
#517
b111 2
1"
#518
0"
#519
b1000 2
1"
#520
0"
#521
b1001 2
1"
#522
0"
#523
b1010 2
1"
#524
0"
#525
b1011 2
1"
#526
0"
#527
b1100 2
1"
#528
0"
#529
b1101 2
1"
#530
0"
#531
b1110 2
1"
#532
0"
#533
b1111 2
1"
#534
0"
#535
b10000 2
1"
#536
0"
#537
b10001 2
1"
#538
0"
#539
b10010 2
1"
#540
0"
#541
b10011 2
1"
#542
0"
#543
b10100 2
1"
#544
0"
#545
b10101 2
1"
#546
0"
#547
b10110 2
1"
#548
0"
#549
b10111 2
1"
#550
0"
#551
b11000 2
1"
#552
0"
#553
b11001 2
1"
#554
0"
#555
b11010 2
1"
#556
0"
#557
b1001 0
1$
1%
b11011 2
1"
#558
0"
#559
0$
0%
b0 2
1"
#560
0"
#561
b1 2
1"
#562
0"
#563
b10 2
1"
#564
0"
#565
b11 2
1"
#566
0"
#567
b100 2
1"
#568
0"
#569
b101 2
1"
#570
0"
#571
b110 2
1"
#572
0"
#573
b111 2
1"
#574
0"
#575
b1000 2
1"
#576
0"
#577
b1001 2
1"
#578
0"
#579
b1010 2
1"
#580
0"
#581
b1011 2
1"
#582
0"
#583
b1100 2
1"
#584
0"
#585
b1101 2
1"
#586
0"
#587
b1110 2
1"
#588
0"
#589
b1111 2
1"
#590
0"
#591
b10000 2
1"
#592
0"
#593
b10001 2
1"
#594
0"
#595
b10010 2
1"
#596
0"
#597
b10011 2
1"
#598
0"
#599
b10100 2
1"
#600
0"
#601
b10101 2
1"
#602
0"
#603
b10110 2
1"
#604
0"
#605
b10111 2
1"
#606
0"
#607
b11000 2
1"
#608
0"
#609
b11001 2
1"
#610
0"
#611
b11010 2
1"
#612
0"
#613
b1010 0
1$
1%
b11011 2
1"
#614
0"
#615
0$
0%
b0 2
1"
#616
0"
#617
b1 2
1"
#618
0"
#619
b10 2
1"
#620
0"
#621
b11 2
1"
#622
0"
#623
b100 2
1"
#624
0"
#625
b101 2
1"
#626
0"
#627
b110 2
1"
#628
0"
#629
b111 2
1"
#630
0"
#631
b1000 2
1"
#632
0"
#633
b1001 2
1"
#634
0"
#635
b1010 2
1"
#636
0"
#637
b1011 2
1"
#638
0"
#639
b1100 2
1"
#640
0"
#641
b1101 2
1"
#642
0"
#643
b1110 2
1"
#644
0"
#645
b1111 2
1"
#646
0"
#647
b10000 2
1"
#648
0"
#649
b10001 2
1"
#650
0"
#651
b10010 2
1"
#652
0"
#653
b10011 2
1"
#654
0"
#655
b10100 2
1"
#656
0"
#657
b10101 2
1"
#658
0"
#659
b10110 2
1"
#660
0"
#661
b10111 2
1"
#662
0"
#663
b11000 2
1"
#664
0"
#665
b11001 2
1"
#666
0"
#667
b11010 2
1"
#668
0"
#669
b1011 0
1$
1%
b11011 2
1"
#670
0"
#671
0$
0%
b0 2
1"
#672
0"
#673
b1 2
1"
#674
0"
#675
b10 2
1"
#676
0"
#677
b11 2
1"
#678
0"
#679
b100 2
1"
#680
0"
#681
b101 2
1"
#682
0"
#683
b110 2
1"
#684
0"
#685
b111 2
1"
#686
0"
#687
b1000 2
1"
#688
0"
#689
b1001 2
1"
#690
0"
#691
b1010 2
1"
#692
0"
#693
b1011 2
1"
#694
0"
#695
b1100 2
1"
#696
0"
#697
b1101 2
1"
#698
0"
#699
b1110 2
1"
#700
0"
#701
b1111 2
1"
#702
0"
#703
b10000 2
1"
#704
0"
#705
b10001 2
1"
#706
0"
#707
b10010 2
1"
#708
0"
#709
b10011 2
1"
#710
0"
#711
b10100 2
1"
#712
0"
#713
b10101 2
1"
#714
0"
#715
b10110 2
1"
#716
0"
#717
b10111 2
1"
#718
0"
#719
b11000 2
1"
#720
0"
#721
b11001 2
1"
#722
0"
#723
b11010 2
1"
#724
0"
#725
b1100 0
1$
1%
b11011 2
1"
#726
0"
#727
0$
0%
b0 2
1"
#728
0"
#729
b1 2
1"
#730
0"
#731
b10 2
1"
#732
0"
#733
b11 2
1"
#734
0"
#735
b100 2
1"
#736
0"
#737
b101 2
1"
#738
0"
#739
b110 2
1"
#740
0"
#741
b111 2
1"
#742
0"
#743
b1000 2
1"
#744
0"
#745
b1001 2
1"
#746
0"
#747
b1010 2
1"
#748
0"
#749
b1011 2
1"
#750
0"
#751
b1100 2
1"
#752
0"
#753
b1101 2
1"
#754
0"
#755
b1110 2
1"
#756
0"
#757
b1111 2
1"
#758
0"
#759
b10000 2
1"
#760
0"
#761
b10001 2
1"
#762
0"
#763
b10010 2
1"
#764
0"
#765
b10011 2
1"
#766
0"
#767
b10100 2
1"
#768
0"
#769
b10101 2
1"
#770
0"
#771
b10110 2
1"
#772
0"
#773
b10111 2
1"
#774
0"
#775
b11000 2
1"
#776
0"
#777
b11001 2
1"
#778
0"
#779
b11010 2
1"
#780
0"
#781
b1101 0
1$
1%
b11011 2
1"
#782
0"
#783
0$
0%
b0 2
1"
#784
0"
#785
b1 2
1"
#786
0"
#787
b10 2
1"
#788
0"
#789
b11 2
1"
#790
0"
#791
b100 2
1"
#792
0"
#793
b101 2
1"
#794
0"
#795
b110 2
1"
#796
0"
#797
b111 2
1"
#798
0"
#799
b1000 2
1"
#800
0"
#801
b1001 2
1"
#802
0"
#803
b1010 2
1"
#804
0"
#805
b1011 2
1"
#806
0"
#807
b1100 2
1"
#808
0"
#809
b1101 2
1"
#810
0"
#811
b1110 2
1"
#812
0"
#813
b1111 2
1"
#814
0"
#815
b10000 2
1"
#816
0"
#817
b10001 2
1"
#818
0"
#819
b10010 2
1"
#820
0"
#821
b10011 2
1"
#822
0"
#823
b10100 2
1"
#824
0"
#825
b10101 2
1"
#826
0"
#827
b10110 2
1"
#828
0"
#829
b10111 2
1"
#830
0"
#831
b11000 2
1"
#832
0"
#833
b11001 2
1"
#834
0"
#835
b11010 2
1"
#836
0"
#837
b1110 0
1$
1%
b11011 2
1"
#838
0"
#839
0$
0%
b0 2
1"
#840
0"
#841
b1 2
1"
#842
0"
#843
b10 2
1"
#844
0"
#845
b11 2
1"
#846
0"
#847
b100 2
1"
#848
0"
#849
b101 2
1"
#850
0"
#851
b110 2
1"
#852
0"
#853
b111 2
1"
#854
0"
#855
b1000 2
1"
#856
0"
#857
b1001 2
1"
#858
0"
#859
b1010 2
1"
#860
0"
#861
b1011 2
1"
#862
0"
#863
b1100 2
1"
#864
0"
#865
b1101 2
1"
#866
0"
#867
b1110 2
1"
#868
0"
#869
b1111 2
1"
#870
0"
#871
b10000 2
1"
#872
0"
#873
b10001 2
1"
#874
0"
#875
b10010 2
1"
#876
0"
#877
b10011 2
1"
#878
0"
#879
b10100 2
1"
#880
0"
#881
b10101 2
1"
#882
0"
#883
b10110 2
1"
#884
0"
#885
b10111 2
1"
#886
0"
#887
b11000 2
1"
#888
0"
#889
b11001 2
1"
#890
0"
#891
b11010 2
1"
#892
0"
#893
b1111 0
1$
1%
b11011 2
1"
#894
0"
#895
0$
0%
b0 2
1"
#896
0"
#897
b1 2
1"
#898
0"
#899
b10 2
1"
#900
0"
#901
b11 2
1"
#902
0"
#903
b100 2
1"
#904
0"
#905
b101 2
1"
#906
0"
#907
b110 2
1"
#908
0"
#909
b111 2
1"
#910
0"
#911
b1000 2
1"
#912
0"
#913
b1001 2
1"
#914
0"
#915
b1010 2
1"
#916
0"
#917
b1011 2
1"
#918
0"
#919
b1100 2
1"
#920
0"
#921
b1101 2
1"
#922
0"
#923
b1110 2
1"
#924
0"
#925
b1111 2
1"
#926
0"
#927
b10000 2
1"
#928
0"
#929
b10001 2
1"
#930
0"
#931
b10010 2
1"
#932
0"
#933
b10011 2
1"
#934
0"
#935
b10100 2
1"
#936
0"
#937
b10101 2
1"
#938
0"
#939
b10110 2
1"
#940
0"
#941
b10111 2
1"
#942
0"
#943
b11000 2
1"
#944
0"
#945
b11001 2
1"
#946
0"
#947
b11010 2
1"
#948
0"
#949
b10000 0
1$
1%
b11011 2
1"
#950
0"
#951
0$
0%
b0 2
1"
#952
0"
#953
b1 2
1"
#954
0"
#955
b10 2
1"
#956
0"
#957
b11 2
1"
#958
0"
#959
b100 2
1"
#960
0"
#961
b101 2
1"
#962
0"
#963
b110 2
1"
#964
0"
#965
b111 2
1"
#966
0"
#967
b1000 2
1"
#968
0"
#969
b1001 2
1"
#970
0"
#971
b1010 2
1"
#972
0"
#973
b1011 2
1"
#974
0"
#975
b1100 2
1"
#976
0"
#977
b1101 2
1"
#978
0"
#979
b1110 2
1"
#980
0"
#981
b1111 2
1"
#982
0"
#983
b10000 2
1"
#984
0"
#985
b10001 2
1"
#986
0"
#987
b10010 2
1"
#988
0"
#989
b10011 2
1"
#990
0"
#991
b10100 2
1"
#992
0"
#993
b10101 2
1"
#994
0"
#995
b10110 2
1"
#996
0"
#997
b10111 2
1"
#998
0"
#999
b11000 2
1"
#1000
0"
#1001
b11001 2
1"
#1002
0"
#1003
b11010 2
1"
#1004
0"
#1005
b10001 0
1$
1%
b11011 2
1"
#1006
0"
#1007
0$
0%
b0 2
1"
#1008
0"
#1009
b1 2
1"
#1010
0"
#1011
b10 2
1"
#1012
0"
#1013
b11 2
1"
#1014
0"
#1015
b100 2
1"
#1016
0"
#1017
b101 2
1"
#1018
0"
#1019
b110 2
1"
#1020
0"
#1021
b111 2
1"
#1022
0"
#1023
b1000 2
1"
#1024
0"
#1025
b1001 2
1"
#1026
0"
#1027
b1010 2
1"
#1028
0"
#1029
b1011 2
1"
#1030
0"
#1031
b1100 2
1"
#1032
0"
#1033
b1101 2
1"
#1034
0"
#1035
b1110 2
1"
#1036
0"
#1037
b1111 2
1"
#1038
0"
#1039
b10000 2
1"
#1040
0"
#1041
b10001 2
1"
#1042
0"
#1043
b10010 2
1"
#1044
0"
#1045
b10011 2
1"
#1046
0"
#1047
b10100 2
1"
#1048
0"
#1049
b10101 2
1"
#1050
0"
#1051
b10110 2
1"
#1052
0"
#1053
b10111 2
1"
#1054
0"
#1055
b11000 2
1"
#1056
0"
#1057
b11001 2
1"
#1058
0"
#1059
b11010 2
1"
#1060
0"
#1061
b10010 0
1$
1%
b11011 2
1"
#1062
0"
#1063
0$
0%
b0 2
1"
#1064
0"
#1065
b1 2
1"
#1066
0"
#1067
b10 2
1"
#1068
0"
#1069
b11 2
1"
#1070
0"
#1071
b100 2
1"
#1072
0"
#1073
b101 2
1"
#1074
0"
#1075
b110 2
1"
#1076
0"
#1077
b111 2
1"
#1078
0"
#1079
b1000 2
1"
#1080
0"
#1081
b1001 2
1"
#1082
0"
#1083
b1010 2
1"
#1084
0"
#1085
b1011 2
1"
#1086
0"
#1087
b1100 2
1"
#1088
0"
#1089
b1101 2
1"
#1090
0"
#1091
b1110 2
1"
#1092
0"
#1093
b1111 2
1"
#1094
0"
#1095
b10000 2
1"
#1096
0"
#1097
b10001 2
1"
#1098
0"
#1099
b10010 2
1"
#1100
0"
#1101
b10011 2
1"
#1102
0"
#1103
b10100 2
1"
#1104
0"
#1105
b10101 2
1"
#1106
0"
#1107
b10110 2
1"
#1108
0"
#1109
b10111 2
1"
#1110
0"
#1111
b11000 2
1"
#1112
0"
#1113
b11001 2
1"
#1114
0"
#1115
b11010 2
1"
#1116
0"
#1117
b10011 0
1$
1%
b11011 2
1"
#1118
0"
#1119
0$
0%
b0 2
1"
#1120
0"
#1121
b1 2
1"
#1122
0"
#1123
b10 2
1"
#1124
0"
#1125
b11 2
1"
#1126
0"
#1127
b100 2
1"
#1128
0"
#1129
b101 2
1"
#1130
0"
#1131
b110 2
1"
#1132
0"
#1133
b111 2
1"
#1134
0"
#1135
b1000 2
1"
#1136
0"
#1137
b1001 2
1"
#1138
0"
#1139
b1010 2
1"
#1140
0"
#1141
b1011 2
1"
#1142
0"
#1143
b1100 2
1"
#1144
0"
#1145
b1101 2
1"
#1146
0"
#1147
b1110 2
1"
#1148
0"
#1149
b1111 2
1"
#1150
0"
#1151
b10000 2
1"
#1152
0"
#1153
b10001 2
1"
#1154
0"
#1155
b10010 2
1"
#1156
0"
#1157
b10011 2
1"
#1158
0"
#1159
b10100 2
1"
#1160
0"
#1161
b10101 2
1"
#1162
0"
#1163
b10110 2
1"
#1164
0"
#1165
b10111 2
1"
#1166
0"
#1167
b11000 2
1"
#1168
0"
#1169
b11001 2
1"
#1170
0"
#1171
b11010 2
1"
#1172
0"
#1173
b10100 0
1$
1%
b11011 2
1"
#1174
0"
#1175
0$
0%
b0 2
1"
#1176
0"
#1177
b1 2
1"
#1178
0"
#1179
b10 2
1"
#1180
0"
#1181
b11 2
1"
#1182
0"
#1183
b100 2
1"
#1184
0"
#1185
b101 2
1"
#1186
0"
#1187
b110 2
1"
#1188
0"
#1189
b111 2
1"
#1190
0"
#1191
b1000 2
1"
#1192
0"
#1193
b1001 2
1"
#1194
0"
#1195
b1010 2
1"
#1196
0"
#1197
b1011 2
1"
#1198
0"
#1199
b1100 2
1"
#1200
0"
#1201
b1101 2
1"
#1202
0"
#1203
b1110 2
1"
#1204
0"
#1205
b1111 2
1"
#1206
0"
#1207
b10000 2
1"
#1208
0"
#1209
b10001 2
1"
#1210
0"
#1211
b10010 2
1"
#1212
0"
#1213
b10011 2
1"
#1214
0"
#1215
b10100 2
1"
#1216
0"
#1217
b10101 2
1"
#1218
0"
#1219
b10110 2
1"
#1220
0"
#1221
b10111 2
1"
#1222
0"
#1223
b11000 2
1"
#1224
0"
#1225
b11001 2
1"
#1226
0"
#1227
b11010 2
1"
#1228
0"
#1229
b10101 0
1$
1%
b11011 2
1"
#1230
0"
#1231
0$
0%
b0 2
1"
#1232
0"
#1233
b1 2
1"
#1234
0"
#1235
b10 2
1"
#1236
0"
#1237
b11 2
1"
#1238
0"
#1239
b100 2
1"
#1240
0"
#1241
b101 2
1"
#1242
0"
#1243
b110 2
1"
#1244
0"
#1245
b111 2
1"
#1246
0"
#1247
b1000 2
1"
#1248
0"
#1249
b1001 2
1"
#1250
0"
#1251
b1010 2
1"
#1252
0"
#1253
b1011 2
1"
#1254
0"
#1255
b1100 2
1"
#1256
0"
#1257
b1101 2
1"
#1258
0"
#1259
b1110 2
1"
#1260
0"
#1261
b1111 2
1"
#1262
0"
#1263
b10000 2
1"
#1264
0"
#1265
b10001 2
1"
#1266
0"
#1267
b10010 2
1"
#1268
0"
#1269
b10011 2
1"
#1270
0"
#1271
b10100 2
1"
#1272
0"
#1273
b10101 2
1"
#1274
0"
#1275
b10110 2
1"
#1276
0"
#1277
b10111 2
1"
#1278
0"
#1279
b11000 2
1"
#1280
0"
#1281
b11001 2
1"
#1282
0"
#1283
b11010 2
1"
#1284
0"
#1285
b10110 0
1$
1%
b11011 2
1"
#1286
0"
#1287
0$
0%
b0 2
1"
#1288
0"
#1289
b1 2
1"
#1290
0"
#1291
b10 2
1"
#1292
0"
#1293
b11 2
1"
